opentaskpy/addons/aws/__init__.py
opentaskpy/addons/aws/remotehandlers/__init__.py
opentaskpy/addons/aws/remotehandlers/creds.py
opentaskpy/addons/aws/remotehandlers/ecsfargate.py
opentaskpy/addons/aws/remotehandlers/lambda.py
opentaskpy/addons/aws/remotehandlers/s3.py
opentaskpy/addons/aws/remotehandlers/schemas/execution/ecsfargate/containerOverrides.json
opentaskpy/addons/aws/remotehandlers/schemas/execution/ecsfargate/ecsfargate.json
opentaskpy/addons/aws/remotehandlers/schemas/execution/ecsfargate/network.json
opentaskpy/addons/aws/remotehandlers/schemas/execution/ecsfargate/protocol.json
opentaskpy/addons/aws/remotehandlers/schemas/execution/lambda/lambda.json
opentaskpy/addons/aws/remotehandlers/schemas/execution/lambda/protocol.json
opentaskpy/addons/aws/remotehandlers/schemas/execution/s3/protocol.json
opentaskpy/addons/aws/remotehandlers/schemas/execution/s3/s3.json
opentaskpy/addons/aws/remotehandlers/schemas/transfer/s3_destination.json
opentaskpy/addons/aws/remotehandlers/schemas/transfer/s3_source.json
opentaskpy/addons/aws/remotehandlers/schemas/transfer/s3_destination/flags.json
opentaskpy/addons/aws/remotehandlers/schemas/transfer/s3_destination/protocol.json
opentaskpy/addons/aws/remotehandlers/schemas/transfer/s3_source/fileWatch.json
opentaskpy/addons/aws/remotehandlers/schemas/transfer/s3_source/protocol.json
opentaskpy/plugins/lookup/aws/ssm.py
otf_addons_aws-0.6.0.dist-info/AUTHORS
otf_addons_aws-0.6.0.dist-info/LICENSE
otf_addons_aws-0.6.0.dist-info/METADATA
otf_addons_aws-0.6.0.dist-info/WHEEL
otf_addons_aws-0.6.0.dist-info/top_level.txt
otf_addons_aws-0.6.0.dist-info/RECORD
