Metadata-Version: 2.1
Name: otf-addons-aws
Version: 0.6.0
Summary: Addons for opentaskpy, giving it the ability to push/pull via AWS S3, and pull variables from AWS SSM Parameter Store.
Author-email: Adam McDonagh <adam@elitemonkey.net>
License: GPLv3
Project-URL: Homepage, https://github.com/adammcdonagh/otf-addons-aws
Project-URL: Bug Tracker, https://github.com/adammcdonagh/otf-addons-aws/issues
Project-URL: Changelog, https://github.com/adammcdonagh/otf-addons-aws/blob/main/CHANGELOG.md
Keywords: automation,task,framework,aws,s3,ssm,otf
Classifier: Programming Language :: Python :: 3
Classifier: License :: OSI Approved :: GNU General Public License v3 (GPLv3)
Classifier: Operating System :: POSIX
Requires-Python: >=3.11
License-File: LICENSE
License-File: AUTHORS
Requires-Dist: boto3 >=1.26
Requires-Dist: opentaskpy >=0.15.0
Provides-Extra: dev
Requires-Dist: awscli ; extra == 'dev'
Requires-Dist: awscli-local ; extra == 'dev'
Requires-Dist: localstack ; extra == 'dev'
Requires-Dist: localstack-client ; extra == 'dev'
Requires-Dist: pytest-shell ; extra == 'dev'
Requires-Dist: types-requests ; extra == 'dev'
Requires-Dist: black >=23.1.0 ; extra == 'dev'
Requires-Dist: isort ; extra == 'dev'
Requires-Dist: pytest ; extra == 'dev'
Requires-Dist: bumpver ; extra == 'dev'
Requires-Dist: lovely-pytest-docker ; extra == 'dev'
Requires-Dist: pre-commit ; extra == 'dev'
Requires-Dist: pylint ; extra == 'dev'
Requires-Dist: pydantic ; extra == 'dev'
Requires-Dist: mypy ; extra == 'dev'
Requires-Dist: ruff ; extra == 'dev'
Requires-Dist: coverage ; extra == 'dev'
Requires-Dist: pytest-cov ; extra == 'dev'
Requires-Dist: moto[ecs] ; extra == 'dev'
